webviz_subsurface_components/GroupTree.py
webviz_subsurface_components/HistoryMatch.py
webviz_subsurface_components/LeafletMap.py
webviz_subsurface_components/Map.py
webviz_subsurface_components/Morris.py
webviz_subsurface_components/PriorPosteriorDistribution.py
webviz_subsurface_components/ReadoutComponent.py
webviz_subsurface_components/SubsurfaceViewer.py
webviz_subsurface_components/VectorCalculator.py
webviz_subsurface_components/VectorCalculatorWrapper.py
webviz_subsurface_components/VectorDefinitions.json
webviz_subsurface_components/VectorDefinitions.py
webviz_subsurface_components/VectorSelector.py
webviz_subsurface_components/ViewAnnotation.py
webviz_subsurface_components/ViewFooter.py
webviz_subsurface_components/WebVizColorLegend.py
webviz_subsurface_components/WebVizContinuousLegend.py
webviz_subsurface_components/WebVizDiscreteLegend.py
webviz_subsurface_components/WellCompletions.py
webviz_subsurface_components/WellLogViewer.py
webviz_subsurface_components/__init__.py
webviz_subsurface_components/_imports_.py
webviz_subsurface_components/async-webviz-group-tree.js
webviz_subsurface_components/async-webviz-group-tree.js.map
webviz_subsurface_components/async-webviz-subsurface-viewer.js
webviz_subsurface_components/async-webviz-subsurface-viewer.js.map
webviz_subsurface_components/async-webviz-view-footer.js
webviz_subsurface_components/async-webviz-view-footer.js.map
webviz_subsurface_components/async-webviz-well-log-viewer.js
webviz_subsurface_components/async-webviz-well-log-viewer.js.map
webviz_subsurface_components/metadata.json
webviz_subsurface_components/package-info.json
webviz_subsurface_components/py_expression_eval.py
webviz_subsurface_components/webviz_subsurface_components.min.js
webviz_subsurface_components/webviz_subsurface_components.min.js.map
webviz_subsurface_components-1.0.4.dist-info/METADATA
webviz_subsurface_components-1.0.4.dist-info/WHEEL
webviz_subsurface_components-1.0.4.dist-info/top_level.txt
webviz_subsurface_components-1.0.4.dist-info/RECORD
